krkn_lib_kubernetes/__init__.py
krkn_lib_kubernetes/client.py
krkn_lib_kubernetes/resources.py
krkn_lib_kubernetes/telemetry.py
krkn_lib_kubernetes/tests/base_test.py
krkn_lib_kubernetes/tests/test_client.py
krkn_lib_kubernetes/tests/test_resources.py
krkn_lib_kubernetes/tests/test_telemetry.py
krkn_lib_kubernetes-0.1.3.dist-info/LICENSE
krkn_lib_kubernetes-0.1.3.dist-info/METADATA
krkn_lib_kubernetes-0.1.3.dist-info/WHEEL
krkn_lib_kubernetes-0.1.3.dist-info/RECORD
